mac_activity_tracker/__init__.py
mac_activity_tracker/_version.py
mac_activity_tracker/config.py
mac_activity_tracker/database.py
mac_activity_tracker/tracker.py
mac_activity_tracker-0.1.5.dist-info/LICENSE
mac_activity_tracker-0.1.5.dist-info/METADATA
mac_activity_tracker-0.1.5.dist-info/WHEEL
mac_activity_tracker-0.1.5.dist-info/entry_points.txt
mac_activity_tracker-0.1.5.dist-info/top_level.txt
mac_activity_tracker-0.1.5.dist-info/RECORD
