Metadata-Version: 2.1
Name: mac-activity-tracker
Version: 0.1.5
Summary: Monitor and analyze your daily work activities
License: Apache License
Keywords: productivity,time-tracking,activity-monitor
Classifier: Development Status :: 3 - Alpha
Classifier: Intended Audience :: End Users/Desktop
Classifier: License :: OSI Approved :: MIT License
Classifier: Programming Language :: Python :: 3
Classifier: Programming Language :: Python :: 3.7
Classifier: Programming Language :: Python :: 3.8
Classifier: Programming Language :: Python :: 3.9
Classifier: Programming Language :: Python :: 3.10
Requires-Python: >=3.7
License-File: LICENSE
Requires-Dist: colorama>=0.4.6
